libetrv/__init__.py
libetrv/bluetooth.py
libetrv/btle.py
libetrv/cli.py
libetrv/data_struct.py
libetrv/device.py
libetrv/exceptions.py
libetrv/properties.py
libetrv/schedule.py
libetrv/utils.py
libetrv/fields/__init__.py
libetrv/fields/base.py
libetrv/fields/bit.py
libetrv/fields/datetime.py
libetrv/fields/enum.py
libetrv/fields/string.py
libetrv/fields/temperature.py
libetrv-0.6.0.dist-info/LICENSE
libetrv-0.6.0.dist-info/METADATA
libetrv-0.6.0.dist-info/WHEEL
libetrv-0.6.0.dist-info/top_level.txt
libetrv-0.6.0.dist-info/RECORD
